nocnus/__init__.py
nocnus/core.py
Nocnus-0.0.7.dist-info/LICENSE
Nocnus-0.0.7.dist-info/METADATA
Nocnus-0.0.7.dist-info/WHEEL
Nocnus-0.0.7.dist-info/top_level.txt
Nocnus-0.0.7.dist-info/RECORD
